bfxapi/__init__.py
bfxapi/_client.py
bfxapi/_utils/__init__.py
bfxapi/_utils/json_decoder.py
bfxapi/_utils/json_encoder.py
bfxapi/_utils/logging.py
bfxapi/_version.py
bfxapi/exceptions.py
bfxapi/py.typed
bfxapi/rest/__init__.py
bfxapi/rest/_bfx_rest_interface.py
bfxapi/rest/_interface/__init__.py
bfxapi/rest/_interface/interface.py
bfxapi/rest/_interface/middleware.py
bfxapi/rest/_interfaces/__init__.py
bfxapi/rest/_interfaces/rest_auth_endpoints.py
bfxapi/rest/_interfaces/rest_merchant_endpoints.py
bfxapi/rest/_interfaces/rest_public_endpoints.py
bfxapi/rest/exceptions.py
bfxapi/types/__init__.py
bfxapi/types/dataclasses.py
bfxapi/types/labeler.py
bfxapi/types/notification.py
bfxapi/types/serializers.py
bfxapi/websocket/__init__.py
bfxapi/websocket/_client/__init__.py
bfxapi/websocket/_client/bfx_websocket_bucket.py
bfxapi/websocket/_client/bfx_websocket_client.py
bfxapi/websocket/_client/bfx_websocket_inputs.py
bfxapi/websocket/_connection.py
bfxapi/websocket/_event_emitter/__init__.py
bfxapi/websocket/_event_emitter/bfx_event_emitter.py
bfxapi/websocket/_handlers/__init__.py
bfxapi/websocket/_handlers/auth_events_handler.py
bfxapi/websocket/_handlers/public_channels_handler.py
bfxapi/websocket/exceptions.py
bfxapi/websocket/subscriptions.py
qubx_bitfinex_api-3.0.7.dist-info/LICENSE
qubx_bitfinex_api-3.0.7.dist-info/METADATA
qubx_bitfinex_api-3.0.7.dist-info/WHEEL
qubx_bitfinex_api-3.0.7.dist-info/RECORD
