Metadata-Version: 2.3
Name: qubx-bitfinex-api
Version: 3.0.7
Summary: Official Bitfinex Python API
License: Apache-2.0
Keywords: bitfinex,api,trading
Author: Yuriy Arabsky
Author-email: yuriy.arabsky@xlydian.com
Requires-Python: >=3.10
Classifier: Development Status :: 5 - Production/Stable
Classifier: Intended Audience :: Developers
Classifier: Topic :: Software Development :: Build Tools
Classifier: Programming Language :: Python :: 3.8
Classifier: Programming Language :: Python :: 3.9
Classifier: Programming Language :: Python :: 3.10
Classifier: Programming Language :: Python :: 3.11
Classifier: Programming Language :: Python :: 3.12
Classifier: Programming Language :: Python :: 3.13
Provides-Extra: dev
Provides-Extra: typing
Requires-Dist: black (==24.2.0) ; extra == "dev"
Requires-Dist: flake8 (==7.0.0) ; extra == "dev"
Requires-Dist: flake8-bugbear (==24.2.6) ; extra == "dev"
Requires-Dist: isort (==5.13.2) ; extra == "dev"
Requires-Dist: mypy (==1.11.0) ; extra == "dev"
Requires-Dist: pre-commit (==3.5.0) ; extra == "dev"
Requires-Dist: pyee (>=11.1.0,<11.2.0)
Requires-Dist: requests (>=2.32.3)
Requires-Dist: types-requests (>=2.32.0.20241016,<2.33.0.0) ; extra == "typing"
Requires-Dist: types-urllib3 (==1.26.25.14) ; extra == "dev"
Requires-Dist: websockets (>=13.0)
Project-URL: Homepage, https://github.com/xLydianSoftware/bitfinex-api-py
Project-URL: Repository, https://github.com/xLydianSoftware/bitfinex-api-py
